PyConText/__init__.py
PyConText/main.py
modulepycontext-0.0.2.dist-info/licenses/LICENSE
modulepycontext-0.0.2.dist-info/METADATA
modulepycontext-0.0.2.dist-info/WHEEL
modulepycontext-0.0.2.dist-info/top_level.txt
modulepycontext-0.0.2.dist-info/RECORD
